{
    "44973": {
        "GreedyRFRBoostDense_upscaleiid": {
            "score_train": [
                0.15278534591197968,
                0.15805314481258392,
                0.15760350227355957,
                0.1660238802433014,
                0.16037312150001526
            ],
            "score_test": [
                0.20057626068592072,
                0.19379070401191711,
                0.2066756933927536,
                0.1970396339893341,
                0.2018609195947647
            ],
            "t_fit": [
                14.166251694783568,
                8.14918614551425,
                6.8596191965043545,
                8.886461153626442,
                4.581959443166852
            ],
            "t_inference": [
                2.9328267239034176,
                1.8069269601255655,
                1.2788704968988895,
                1.7930432204157114,
                1.0981817729771137
            ],
            "hyperparams": [
                {
                    "in_dim": 12,
                    "out_dim": 1,
                    "feature_type": "SWIM",
                    "upscale_type": "iid",
                    "randfeat_xt_dim": 512,
                    "randfeat_x0_dim": 512,
                    "sandwich_solver": "dense",
                    "n_layers": 15,
                    "hidden_dim": 496,
                    "l2_reg": 0.8663027281362005,
                    "l2_ghat": 1.2438016402029588e-07,
                    "boost_lr": 0.9,
                    "SWIM_scale": 0.47445961181929874
                },
                {
                    "in_dim": 12,
                    "out_dim": 1,
                    "feature_type": "SWIM",
                    "upscale_type": "iid",
                    "randfeat_xt_dim": 512,
                    "randfeat_x0_dim": 512,
                    "sandwich_solver": "dense",
                    "n_layers": 12,
                    "hidden_dim": 464,
                    "l2_reg": 0.4740312426012213,
                    "l2_ghat": 1.9834052310970197e-07,
                    "boost_lr": 0.9,
                    "SWIM_scale": 0.4794908130063667
                },
                {
                    "in_dim": 12,
                    "out_dim": 1,
                    "feature_type": "SWIM",
                    "upscale_type": "iid",
                    "randfeat_xt_dim": 512,
                    "randfeat_x0_dim": 512,
                    "sandwich_solver": "dense",
                    "n_layers": 15,
                    "hidden_dim": 208,
                    "l2_reg": 0.18574627210040454,
                    "l2_ghat": 3.047814846601364e-06,
                    "boost_lr": 0.9,
                    "SWIM_scale": 0.5896796169783327
                },
                {
                    "in_dim": 12,
                    "out_dim": 1,
                    "feature_type": "SWIM",
                    "upscale_type": "iid",
                    "randfeat_xt_dim": 512,
                    "randfeat_x0_dim": 512,
                    "sandwich_solver": "dense",
                    "n_layers": 15,
                    "hidden_dim": 304,
                    "l2_reg": 0.7580098321944119,
                    "l2_ghat": 7.943364481078054e-07,
                    "boost_lr": 0.8,
                    "SWIM_scale": 0.5066680903022541
                },
                {
                    "in_dim": 12,
                    "out_dim": 1,
                    "feature_type": "SWIM",
                    "upscale_type": "iid",
                    "randfeat_xt_dim": 512,
                    "randfeat_x0_dim": 512,
                    "sandwich_solver": "dense",
                    "n_layers": 9,
                    "hidden_dim": 336,
                    "l2_reg": 0.6720074049490165,
                    "l2_ghat": 2.838699478563516e-07,
                    "boost_lr": 0.9,
                    "SWIM_scale": 0.48797912388953724
                }
            ]
        }
    }
}