{
    "44983": {
        "Ridge": {
            "score_train": [
                0.4295637905597687,
                0.42885932326316833,
                0.4304443299770355,
                0.4277536869049072,
                0.42921462655067444
            ],
            "score_test": [
                0.42914849519729614,
                0.43288397789001465,
                0.42676839232444763,
                0.4371667206287384,
                0.4310529828071594
            ],
            "t_fit": [
                0.001531757414340973,
                0.0011966563761234283,
                0.0012078732252120972,
                0.0014113076031208038,
                0.0012760423123836517
            ],
            "t_inference": [
                0.00010472908616065979,
                8.488073945045471e-05,
                8.090212941169739e-05,
                0.00011132284998893738,
                0.00010635703802108765
            ],
            "hyperparams": [
                {
                    "l2_reg": 0.0008682350521060755
                },
                {
                    "l2_reg": 0.0018451468102544245
                },
                {
                    "l2_reg": 0.000523197923158906
                },
                {
                    "l2_reg": 0.0011112358283645242
                },
                {
                    "l2_reg": 0.0003830601677899827
                }
            ]
        }
    }
}