{
    "44974": {
        "RFNN": {
            "score_train": [
                0.19418971240520477,
                0.1834421008825302,
                0.1760142296552658,
                0.17813725769519806,
                0.1829957664012909
            ],
            "score_test": [
                0.20622366666793823,
                0.2160494327545166,
                0.22622191905975342,
                0.20693282783031464,
                0.20321409404277802
            ],
            "t_fit": [
                0.10066734254360199,
                0.08589654788374901,
                0.10738879814743996,
                0.12881669774651527,
                0.08516297861933708
            ],
            "t_inference": [
                0.03111005201935768,
                0.026563063263893127,
                0.03425319492816925,
                0.03662627935409546,
                0.027488835155963898
            ],
            "hyperparams": [
                {
                    "n_layers": 0,
                    "in_dim": 24,
                    "out_dim": 1,
                    "upscale_type": "SWIM",
                    "activation": "tanh",
                    "use_batchnorm": false,
                    "l2_reg": 2.1168021906243256e-05,
                    "hidden_dim": 487,
                    "SWIM_scale": 0.9928539784780369
                },
                {
                    "n_layers": 0,
                    "in_dim": 24,
                    "out_dim": 1,
                    "upscale_type": "SWIM",
                    "activation": "tanh",
                    "use_batchnorm": false,
                    "l2_reg": 1.7251631203288545e-05,
                    "hidden_dim": 504,
                    "SWIM_scale": 1.2860970008681698
                },
                {
                    "n_layers": 0,
                    "in_dim": 24,
                    "out_dim": 1,
                    "upscale_type": "SWIM",
                    "activation": "tanh",
                    "use_batchnorm": false,
                    "l2_reg": 1.0051480539912704e-05,
                    "hidden_dim": 503,
                    "SWIM_scale": 1.1738190052111321
                },
                {
                    "n_layers": 0,
                    "in_dim": 24,
                    "out_dim": 1,
                    "upscale_type": "SWIM",
                    "activation": "tanh",
                    "use_batchnorm": false,
                    "l2_reg": 1.459411586759831e-05,
                    "hidden_dim": 502,
                    "SWIM_scale": 1.2111900939897735
                },
                {
                    "n_layers": 0,
                    "in_dim": 24,
                    "out_dim": 1,
                    "upscale_type": "SWIM",
                    "activation": "tanh",
                    "use_batchnorm": false,
                    "l2_reg": 2.2678541613471244e-05,
                    "hidden_dim": 512,
                    "SWIM_scale": 1.2054545102647733
                }
            ]
        }
    }
}