{
    "44980": {
        "RandomFeatureNetwork_iid_relu": {
            "score_train": [
                0.44373729825019836,
                0.43912073969841003,
                0.4413723945617676,
                0.43391311168670654,
                0.4402686357498169
            ],
            "score_test": [
                0.45017409324645996,
                0.4786814749240875,
                0.4642546474933624,
                0.5100546479225159,
                0.47320815920829773
            ],
            "t_fit": [
                0.07109557092189789,
                0.06150992959737778,
                0.08204568922519684,
                0.08837676793336868,
                0.08847279846668243
            ],
            "t_inference": [
                0.007211282849311829,
                0.01038246601819992,
                0.00734497606754303,
                0.011995747685432434,
                0.01101984828710556
            ],
            "hyperparams": [
                {
                    "n_layers": 0,
                    "in_dim": 8,
                    "out_dim": 1,
                    "upscale_type": "iid",
                    "activation": "relu",
                    "hidden_dim": 495,
                    "iid_scale": 1.1010000142864829,
                    "l2_reg": 0.0021009418496219768
                },
                {
                    "n_layers": 0,
                    "in_dim": 8,
                    "out_dim": 1,
                    "upscale_type": "iid",
                    "activation": "relu",
                    "hidden_dim": 495,
                    "iid_scale": 1.1010000142864829,
                    "l2_reg": 0.0021009418496219768
                },
                {
                    "n_layers": 0,
                    "in_dim": 8,
                    "out_dim": 1,
                    "upscale_type": "iid",
                    "activation": "relu",
                    "hidden_dim": 495,
                    "iid_scale": 1.1010000142864829,
                    "l2_reg": 0.0021009418496219768
                },
                {
                    "n_layers": 0,
                    "in_dim": 8,
                    "out_dim": 1,
                    "upscale_type": "iid",
                    "activation": "relu",
                    "hidden_dim": 495,
                    "iid_scale": 1.1010000142864829,
                    "l2_reg": 0.0021009418496219768
                },
                {
                    "n_layers": 0,
                    "in_dim": 8,
                    "out_dim": 1,
                    "upscale_type": "iid",
                    "activation": "relu",
                    "hidden_dim": 495,
                    "iid_scale": 1.1010000142864829,
                    "l2_reg": 0.0021009418496219768
                }
            ]
        }
    }
}