{
    "44990": {
        "GradientRFRBoostID_relu": {
            "score_train": [
                0.3832826316356659,
                0.3849893808364868,
                0.379472017288208,
                0.3859268128871918,
                0.381401926279068
            ],
            "score_test": [
                0.397337943315506,
                0.38656166195869446,
                0.3986009359359741,
                0.41084393858909607,
                0.4045555889606476
            ],
            "t_fit": [
                1.641384094953537,
                0.47407475486397743,
                0.9086664468050003,
                2.3986510038375854,
                1.194471538066864
            ],
            "t_inference": [
                0.21242820098996162,
                0.06446292996406555,
                0.11470670998096466,
                0.32715555652976036,
                0.14540154486894608
            ],
            "hyperparams": [
                {
                    "in_dim": 49,
                    "out_dim": 1,
                    "feature_type": "SWIM",
                    "upscale_type": "identity",
                    "randfeat_xt_dim": 512,
                    "randfeat_x0_dim": 512,
                    "activation": "relu",
                    "n_layers": 7,
                    "hidden_dim": 61,
                    "l2_reg": 0.19276154014685384,
                    "l2_ghat": 0.0747142925697627,
                    "boost_lr": 0.6,
                    "SWIM_scale": 0.4512366786165506,
                    "iid_scale": 6.208234720566068
                },
                {
                    "in_dim": 49,
                    "out_dim": 1,
                    "feature_type": "SWIM",
                    "upscale_type": "identity",
                    "randfeat_xt_dim": 512,
                    "randfeat_x0_dim": 512,
                    "activation": "relu",
                    "n_layers": 2,
                    "hidden_dim": 126,
                    "l2_reg": 0.15876391057145323,
                    "l2_ghat": 0.16519123913033668,
                    "boost_lr": 0.6,
                    "SWIM_scale": 1.9292395440080992,
                    "iid_scale": 0.13274544714535272
                },
                {
                    "in_dim": 49,
                    "out_dim": 1,
                    "feature_type": "SWIM",
                    "upscale_type": "identity",
                    "randfeat_xt_dim": 512,
                    "randfeat_x0_dim": 512,
                    "activation": "relu",
                    "n_layers": 4,
                    "hidden_dim": 239,
                    "l2_reg": 0.03996171193727945,
                    "l2_ghat": 0.00452867111781475,
                    "boost_lr": 0.6,
                    "SWIM_scale": 0.13965134344995722,
                    "iid_scale": 4.873198729727085
                },
                {
                    "in_dim": 49,
                    "out_dim": 1,
                    "feature_type": "SWIM",
                    "upscale_type": "identity",
                    "randfeat_xt_dim": 512,
                    "randfeat_x0_dim": 512,
                    "activation": "relu",
                    "n_layers": 10,
                    "hidden_dim": 128,
                    "l2_reg": 0.272469128311653,
                    "l2_ghat": 0.04517346932663777,
                    "boost_lr": 0.5,
                    "SWIM_scale": -0.7810487622992588,
                    "iid_scale": 0.15222359594746435
                },
                {
                    "in_dim": 49,
                    "out_dim": 1,
                    "feature_type": "SWIM",
                    "upscale_type": "identity",
                    "randfeat_xt_dim": 512,
                    "randfeat_x0_dim": 512,
                    "activation": "relu",
                    "n_layers": 4,
                    "hidden_dim": 148,
                    "l2_reg": 0.2756650198925821,
                    "l2_ghat": 0.19732507387957332,
                    "boost_lr": 0.6,
                    "SWIM_scale": 1.363474907775562,
                    "iid_scale": 0.3808624727407669
                }
            ]
        }
    }
}