{
    "44964": {
        "GreedyRFRBoostDiag_batchnormFalse": {
            "score_train": [
                0.3586769104003906,
                0.3565635085105896,
                0.36004361510276794,
                0.34770068526268005,
                0.3628278076648712
            ],
            "score_test": [
                0.3907642364501953,
                0.4034000337123871,
                0.41732266545295715,
                0.4281652569770813,
                0.4203115403652191
            ],
            "t_fit": [
                2.7706668078899384,
                3.822045713663101,
                2.8382193595170975,
                2.382683228701353,
                3.341954354196787
            ],
            "t_inference": [
                0.7799702398478985,
                1.2218527644872665,
                0.8153152465820312,
                0.7490107491612434,
                1.1398338004946709
            ],
            "hyperparams": [
                {
                    "in_dim": 81,
                    "out_dim": 1,
                    "feature_type": "SWIM",
                    "upscale_type": "SWIM",
                    "randfeat_xt_dim": 512,
                    "randfeat_x0_dim": 512,
                    "sandwich_solver": "diag",
                    "activation": "tanh",
                    "use_batchnorm": false,
                    "n_layers": 8,
                    "l2_reg": 0.00014846878432070573,
                    "l2_ghat": 1.5700378884267187e-05,
                    "boost_lr": 0.7595760793712335,
                    "hidden_dim": 512,
                    "SWIM_scale": 1.0834773323820617
                },
                {
                    "in_dim": 81,
                    "out_dim": 1,
                    "feature_type": "SWIM",
                    "upscale_type": "SWIM",
                    "randfeat_xt_dim": 512,
                    "randfeat_x0_dim": 512,
                    "sandwich_solver": "diag",
                    "activation": "tanh",
                    "use_batchnorm": false,
                    "n_layers": 9,
                    "l2_reg": 0.00021279997218644672,
                    "l2_ghat": 1.4051565975833304e-05,
                    "boost_lr": 0.6752642804302235,
                    "hidden_dim": 473,
                    "SWIM_scale": 1.1952274080447158
                },
                {
                    "in_dim": 81,
                    "out_dim": 1,
                    "feature_type": "SWIM",
                    "upscale_type": "SWIM",
                    "randfeat_xt_dim": 512,
                    "randfeat_x0_dim": 512,
                    "sandwich_solver": "diag",
                    "activation": "tanh",
                    "use_batchnorm": false,
                    "n_layers": 9,
                    "l2_reg": 0.00016127941963344503,
                    "l2_ghat": 1.0524513854532658e-05,
                    "boost_lr": 0.6168212201037259,
                    "hidden_dim": 480,
                    "SWIM_scale": 0.8493703370441935
                },
                {
                    "in_dim": 81,
                    "out_dim": 1,
                    "feature_type": "SWIM",
                    "upscale_type": "SWIM",
                    "randfeat_xt_dim": 512,
                    "randfeat_x0_dim": 512,
                    "sandwich_solver": "diag",
                    "activation": "tanh",
                    "use_batchnorm": false,
                    "n_layers": 8,
                    "l2_reg": 3.814728450588199e-05,
                    "l2_ghat": 0.0001380082724417064,
                    "boost_lr": 0.9304264154149124,
                    "hidden_dim": 468,
                    "SWIM_scale": 1.1444170923998003
                },
                {
                    "in_dim": 81,
                    "out_dim": 1,
                    "feature_type": "SWIM",
                    "upscale_type": "SWIM",
                    "randfeat_xt_dim": 512,
                    "randfeat_x0_dim": 512,
                    "sandwich_solver": "diag",
                    "activation": "tanh",
                    "use_batchnorm": false,
                    "n_layers": 8,
                    "l2_reg": 0.00020096364771234838,
                    "l2_ghat": 4.6923680262781995e-05,
                    "boost_lr": 0.5595237457768454,
                    "hidden_dim": 507,
                    "SWIM_scale": 1.1451814141198653
                }
            ]
        }
    }
}