{
    "44956": {
        "GreedyRFRBoostDense_upscaleiid": {
            "score_train": [
                0.6030214428901672,
                0.5941395163536072,
                0.5982908606529236,
                0.5862945914268494,
                0.5973019599914551
            ],
            "score_test": [
                0.5897446870803833,
                0.5979193449020386,
                0.6238507032394409,
                0.652388334274292,
                0.6131972670555115
            ],
            "t_fit": [
                6.569156527519226,
                3.3246419578790665,
                7.281486032530665,
                6.711307650431991,
                8.769940059632063
            ],
            "t_inference": [
                0.9619994964450598,
                0.5714559350162745,
                1.2383538875728846,
                1.0646635796874762,
                2.074851719662547
            ],
            "hyperparams": [
                {
                    "in_dim": 10,
                    "out_dim": 1,
                    "feature_type": "SWIM",
                    "upscale_type": "iid",
                    "randfeat_xt_dim": 512,
                    "randfeat_x0_dim": 512,
                    "sandwich_solver": "dense",
                    "n_layers": 19,
                    "hidden_dim": 144,
                    "l2_reg": 0.029464744415944055,
                    "l2_ghat": 0.35732303434954055,
                    "boost_lr": 0.7,
                    "SWIM_scale": 1.3950224487900573
                },
                {
                    "in_dim": 10,
                    "out_dim": 1,
                    "feature_type": "SWIM",
                    "upscale_type": "iid",
                    "randfeat_xt_dim": 512,
                    "randfeat_x0_dim": 512,
                    "sandwich_solver": "dense",
                    "n_layers": 9,
                    "hidden_dim": 208,
                    "l2_reg": 0.008342808863803968,
                    "l2_ghat": 0.5003163480572157,
                    "boost_lr": 0.8,
                    "SWIM_scale": 1.4101734298403645
                },
                {
                    "in_dim": 10,
                    "out_dim": 1,
                    "feature_type": "SWIM",
                    "upscale_type": "iid",
                    "randfeat_xt_dim": 512,
                    "randfeat_x0_dim": 512,
                    "sandwich_solver": "dense",
                    "n_layers": 20,
                    "hidden_dim": 208,
                    "l2_reg": 0.5051858095330883,
                    "l2_ghat": 0.03522916342082817,
                    "boost_lr": 0.9,
                    "SWIM_scale": 0.9548772231061105
                },
                {
                    "in_dim": 10,
                    "out_dim": 1,
                    "feature_type": "SWIM",
                    "upscale_type": "iid",
                    "randfeat_xt_dim": 512,
                    "randfeat_x0_dim": 512,
                    "sandwich_solver": "dense",
                    "n_layers": 19,
                    "hidden_dim": 176,
                    "l2_reg": 0.14123112374031696,
                    "l2_ghat": 0.003683815378977155,
                    "boost_lr": 0.9,
                    "SWIM_scale": 0.3930883199352137
                },
                {
                    "in_dim": 10,
                    "out_dim": 1,
                    "feature_type": "SWIM",
                    "upscale_type": "iid",
                    "randfeat_xt_dim": 512,
                    "randfeat_x0_dim": 512,
                    "sandwich_solver": "dense",
                    "n_layers": 20,
                    "hidden_dim": 432,
                    "l2_reg": 0.7380188736887553,
                    "l2_ghat": 0.010977468191761645,
                    "boost_lr": 0.6,
                    "SWIM_scale": 0.9142229756833911
                }
            ]
        }
    }
}