{
    "4538": {
        "RFRBoost_upscaleiid_batchnormFalse": {
            "score_train": [
                -0.6492499709129333,
                -0.6700000166893005,
                -0.6955000162124634,
                -0.6417499780654907,
                -0.6884999871253967
            ],
            "score_test": [
                -0.5699999928474426,
                -0.5699999928474426,
                -0.5680000185966492,
                -0.5339999794960022,
                -0.5400000214576721
            ],
            "t_fit": [
                1.264648750424385,
                4.5645431987941265,
                4.01335821673274,
                3.1298439130187035,
                3.183100689202547
            ],
            "t_inference": [
                0.20135045424103737,
                0.8705414086580276,
                0.5589574612677097,
                0.6020948067307472,
                0.45830946415662766
            ],
            "hyperparams": [
                {
                    "in_dim": 32,
                    "n_classes": 5,
                    "feature_type": "SWIM",
                    "upscale_type": "iid",
                    "randfeat_xt_dim": 512,
                    "randfeat_x0_dim": 512,
                    "activation": "tanh",
                    "use_batchnorm": false,
                    "do_linesearch": true,
                    "n_layers": 3,
                    "hidden_dim": 122,
                    "l2_cls": 0.010887872190692479,
                    "l2_ghat": 0.23916547826312404,
                    "boost_lr": 0.29901232008696355,
                    "SWIM_scale": 1.5277311495315844
                },
                {
                    "in_dim": 32,
                    "n_classes": 5,
                    "feature_type": "SWIM",
                    "upscale_type": "iid",
                    "randfeat_xt_dim": 512,
                    "randfeat_x0_dim": 512,
                    "activation": "tanh",
                    "use_batchnorm": false,
                    "do_linesearch": true,
                    "n_layers": 5,
                    "hidden_dim": 510,
                    "l2_cls": 0.015460171069547224,
                    "l2_ghat": 0.060284583866645584,
                    "boost_lr": 0.10003008625865827,
                    "SWIM_scale": 1.54289756504873
                },
                {
                    "in_dim": 32,
                    "n_classes": 5,
                    "feature_type": "SWIM",
                    "upscale_type": "iid",
                    "randfeat_xt_dim": 512,
                    "randfeat_x0_dim": 512,
                    "activation": "tanh",
                    "use_batchnorm": false,
                    "do_linesearch": true,
                    "n_layers": 5,
                    "hidden_dim": 312,
                    "l2_cls": 0.0017703419818568358,
                    "l2_ghat": 0.49043823980925366,
                    "boost_lr": 0.21054949994636038,
                    "SWIM_scale": 1.6947145270886605
                },
                {
                    "in_dim": 32,
                    "n_classes": 5,
                    "feature_type": "SWIM",
                    "upscale_type": "iid",
                    "randfeat_xt_dim": 512,
                    "randfeat_x0_dim": 512,
                    "activation": "tanh",
                    "use_batchnorm": false,
                    "do_linesearch": true,
                    "n_layers": 5,
                    "hidden_dim": 293,
                    "l2_cls": 0.03786110908762667,
                    "l2_ghat": 0.4520270604917945,
                    "boost_lr": 0.25476545691388736,
                    "SWIM_scale": 1.2159384920068723
                },
                {
                    "in_dim": 32,
                    "n_classes": 5,
                    "feature_type": "SWIM",
                    "upscale_type": "iid",
                    "randfeat_xt_dim": 512,
                    "randfeat_x0_dim": 512,
                    "activation": "tanh",
                    "use_batchnorm": false,
                    "do_linesearch": true,
                    "n_layers": 5,
                    "hidden_dim": 232,
                    "l2_cls": 0.0016978197556003758,
                    "l2_ghat": 1.8888479217332022,
                    "boost_lr": 0.3683988795134028,
                    "SWIM_scale": 1.8328600424117627
                }
            ]
        }
    }
}