{
    "50": {
        "RFRBoost_ID_batchnormFalse": {
            "score_train": [
                -1.0,
                -1.0,
                -1.0,
                -1.0,
                -1.0
            ],
            "score_test": [
                -0.984375,
                -0.9739583134651184,
                -1.0,
                -0.9842932224273682,
                -1.0
            ],
            "t_fit": [
                1.1258315481245518,
                1.2422703728079796,
                0.9725334532558918,
                0.22575668618083,
                1.8193659782409668
            ],
            "t_inference": [
                0.08655469492077827,
                0.09158466011285782,
                0.07251808792352676,
                0.015198219567537308,
                0.12736889719963074
            ],
            "hyperparams": [
                {
                    "in_dim": 27,
                    "n_classes": 2,
                    "feature_type": "SWIM",
                    "upscale_type": "identity",
                    "randfeat_xt_dim": 512,
                    "randfeat_x0_dim": 512,
                    "activation": "tanh",
                    "use_batchnorm": false,
                    "do_linesearch": true,
                    "n_layers": 6,
                    "hidden_dim": 27,
                    "l2_cls": 0.010565190237044256,
                    "l2_ghat": 4.529796020196815e-05,
                    "boost_lr": 0.35180219762131004,
                    "SWIM_scale": 0.5503903838122075
                },
                {
                    "in_dim": 27,
                    "n_classes": 2,
                    "feature_type": "SWIM",
                    "upscale_type": "identity",
                    "randfeat_xt_dim": 512,
                    "randfeat_x0_dim": 512,
                    "activation": "tanh",
                    "use_batchnorm": false,
                    "do_linesearch": true,
                    "n_layers": 7,
                    "hidden_dim": 27,
                    "l2_cls": 0.001721480255342043,
                    "l2_ghat": 7.564832875444999e-05,
                    "boost_lr": 0.5309790452053765,
                    "SWIM_scale": 0.5545329465801383
                },
                {
                    "in_dim": 27,
                    "n_classes": 2,
                    "feature_type": "SWIM",
                    "upscale_type": "identity",
                    "randfeat_xt_dim": 512,
                    "randfeat_x0_dim": 512,
                    "activation": "tanh",
                    "use_batchnorm": false,
                    "do_linesearch": true,
                    "n_layers": 5,
                    "hidden_dim": 27,
                    "l2_cls": 8.580932978114173e-05,
                    "l2_ghat": 0.00010754877779343985,
                    "boost_lr": 0.5860041352625208,
                    "SWIM_scale": 0.8514964575313226
                },
                {
                    "in_dim": 27,
                    "n_classes": 2,
                    "feature_type": "SWIM",
                    "upscale_type": "identity",
                    "randfeat_xt_dim": 512,
                    "randfeat_x0_dim": 512,
                    "activation": "tanh",
                    "use_batchnorm": false,
                    "do_linesearch": true,
                    "n_layers": 1,
                    "hidden_dim": 27,
                    "l2_cls": 0.009355380606452175,
                    "l2_ghat": 1.6081669283634658e-05,
                    "boost_lr": 0.8115595675970501,
                    "SWIM_scale": 0.49935297516002286
                },
                {
                    "in_dim": 27,
                    "n_classes": 2,
                    "feature_type": "SWIM",
                    "upscale_type": "identity",
                    "randfeat_xt_dim": 512,
                    "randfeat_x0_dim": 512,
                    "activation": "tanh",
                    "use_batchnorm": false,
                    "do_linesearch": true,
                    "n_layers": 9,
                    "hidden_dim": 27,
                    "l2_cls": 0.0015590838195898426,
                    "l2_ghat": 0.001009518143328422,
                    "boost_lr": 0.3834126200489384,
                    "SWIM_scale": 1.0790926920851174
                }
            ]
        }
    }
}