{
    "11": {
        "RFRBoost_ID_batchnormFalse": {
            "score_train": [
                -0.9980000257492065,
                -1.0,
                -0.9900000095367432,
                -1.0,
                -0.984000027179718
            ],
            "score_test": [
                -0.9760000109672546,
                -0.9919999837875366,
                -0.984000027179718,
                -0.9679999947547913,
                -0.9279999732971191
            ],
            "t_fit": [
                0.6449216976761818,
                0.8517691791057587,
                0.6791378073394299,
                0.8201330974698067,
                0.6857384517788887
            ],
            "t_inference": [
                0.02080763876438141,
                0.026583366096019745,
                0.02292957901954651,
                0.026363231241703033,
                0.02619190514087677
            ],
            "hyperparams": [
                {
                    "in_dim": 4,
                    "n_classes": 3,
                    "feature_type": "SWIM",
                    "upscale_type": "identity",
                    "randfeat_xt_dim": 512,
                    "randfeat_x0_dim": 512,
                    "activation": "tanh",
                    "use_batchnorm": false,
                    "do_linesearch": true,
                    "n_layers": 4,
                    "hidden_dim": 20,
                    "l2_cls": 3.7755223363354274e-06,
                    "l2_ghat": 4.951075384079674,
                    "boost_lr": 0.9394516018106462,
                    "SWIM_scale": 1.5384475942019067
                },
                {
                    "in_dim": 4,
                    "n_classes": 3,
                    "feature_type": "SWIM",
                    "upscale_type": "identity",
                    "randfeat_xt_dim": 512,
                    "randfeat_x0_dim": 512,
                    "activation": "tanh",
                    "use_batchnorm": false,
                    "do_linesearch": true,
                    "n_layers": 5,
                    "hidden_dim": 46,
                    "l2_cls": 1.5687861264974692e-06,
                    "l2_ghat": 0.008073675030986086,
                    "boost_lr": 0.7893072877695659,
                    "SWIM_scale": 0.38155055828413686
                },
                {
                    "in_dim": 4,
                    "n_classes": 3,
                    "feature_type": "SWIM",
                    "upscale_type": "identity",
                    "randfeat_xt_dim": 512,
                    "randfeat_x0_dim": 512,
                    "activation": "tanh",
                    "use_batchnorm": false,
                    "do_linesearch": true,
                    "n_layers": 4,
                    "hidden_dim": 98,
                    "l2_cls": 4.661127470530013e-06,
                    "l2_ghat": 1.663162303580757,
                    "boost_lr": 0.7700503665237035,
                    "SWIM_scale": 0.7307755786765004
                },
                {
                    "in_dim": 4,
                    "n_classes": 3,
                    "feature_type": "SWIM",
                    "upscale_type": "identity",
                    "randfeat_xt_dim": 512,
                    "randfeat_x0_dim": 512,
                    "activation": "tanh",
                    "use_batchnorm": false,
                    "do_linesearch": true,
                    "n_layers": 5,
                    "hidden_dim": 110,
                    "l2_cls": 1.114874900066028e-05,
                    "l2_ghat": 3.4199479530931094,
                    "boost_lr": 0.9215987113760741,
                    "SWIM_scale": 1.822525193308154
                },
                {
                    "in_dim": 4,
                    "n_classes": 3,
                    "feature_type": "SWIM",
                    "upscale_type": "identity",
                    "randfeat_xt_dim": 512,
                    "randfeat_x0_dim": 512,
                    "activation": "tanh",
                    "use_batchnorm": false,
                    "do_linesearch": true,
                    "n_layers": 5,
                    "hidden_dim": 16,
                    "l2_cls": 0.07881781856764801,
                    "l2_ghat": 9.523078504104781,
                    "boost_lr": 0.990380058955877,
                    "SWIM_scale": 1.636525924696849
                }
            ]
        }
    }
}