{
    "28": {
        "RFRBoost_upscaleiid_linesearchFalse": {
            "score_train": [
                -1.0,
                -1.0,
                -1.0,
                -1.0,
                -1.0
            ],
            "score_test": [
                -0.9950000047683716,
                -0.9819999933242798,
                -0.9890000224113464,
                -0.984000027179718,
                -0.9900000095367432
            ],
            "t_fit": [
                2.1535368897020817,
                5.417206339538097,
                2.817284855991602,
                3.8040713258087635,
                3.727255254983902
            ],
            "t_inference": [
                0.27999189868569374,
                0.8660131618380547,
                0.4461824335157871,
                0.6640908867120743,
                0.6370058953762054
            ],
            "hyperparams": [
                {
                    "in_dim": 64,
                    "n_classes": 10,
                    "feature_type": "SWIM",
                    "upscale_type": "iid",
                    "randfeat_xt_dim": 512,
                    "randfeat_x0_dim": 512,
                    "activation": "tanh",
                    "use_batchnorm": true,
                    "do_linesearch": false,
                    "n_layers": 5,
                    "hidden_dim": 46,
                    "l2_cls": 6.885640636075721e-05,
                    "l2_ghat": 0.000329074459345716,
                    "boost_lr": 0.5386295120918512,
                    "SWIM_scale": 1.4635249002460213
                },
                {
                    "in_dim": 64,
                    "n_classes": 10,
                    "feature_type": "SWIM",
                    "upscale_type": "iid",
                    "randfeat_xt_dim": 512,
                    "randfeat_x0_dim": 512,
                    "activation": "tanh",
                    "use_batchnorm": true,
                    "do_linesearch": false,
                    "n_layers": 5,
                    "hidden_dim": 473,
                    "l2_cls": 0.00011543614165524664,
                    "l2_ghat": 0.00015147263147841542,
                    "boost_lr": 0.8614170610577238,
                    "SWIM_scale": 1.7136067950207958
                },
                {
                    "in_dim": 64,
                    "n_classes": 10,
                    "feature_type": "SWIM",
                    "upscale_type": "iid",
                    "randfeat_xt_dim": 512,
                    "randfeat_x0_dim": 512,
                    "activation": "tanh",
                    "use_batchnorm": true,
                    "do_linesearch": false,
                    "n_layers": 5,
                    "hidden_dim": 173,
                    "l2_cls": 0.00044442754554589216,
                    "l2_ghat": 0.0004731789127065243,
                    "boost_lr": 0.759682742241198,
                    "SWIM_scale": 1.5657143172698877
                },
                {
                    "in_dim": 64,
                    "n_classes": 10,
                    "feature_type": "SWIM",
                    "upscale_type": "iid",
                    "randfeat_xt_dim": 512,
                    "randfeat_x0_dim": 512,
                    "activation": "tanh",
                    "use_batchnorm": true,
                    "do_linesearch": false,
                    "n_layers": 5,
                    "hidden_dim": 295,
                    "l2_cls": 0.0001680768581194343,
                    "l2_ghat": 0.00017076184667800222,
                    "boost_lr": 0.9487163903920499,
                    "SWIM_scale": 1.9670195781837405
                },
                {
                    "in_dim": 64,
                    "n_classes": 10,
                    "feature_type": "SWIM",
                    "upscale_type": "iid",
                    "randfeat_xt_dim": 512,
                    "randfeat_x0_dim": 512,
                    "activation": "tanh",
                    "use_batchnorm": true,
                    "do_linesearch": false,
                    "n_layers": 5,
                    "hidden_dim": 204,
                    "l2_cls": 0.0004891677014466756,
                    "l2_ghat": 0.00016341062970233572,
                    "boost_lr": 0.9927173149488642,
                    "SWIM_scale": 1.7188119013304723
                }
            ]
        }
    }
}