{
    "40701": {
        "RFRBoost_ID_linesearchFalse_batchnormFalse": {
            "score_train": [
                -0.9624999761581421,
                -0.9592499732971191,
                -0.9670000076293945,
                -0.9647499918937683,
                -0.9570000171661377
            ],
            "score_test": [
                -0.9340000152587891,
                -0.9340000152587891,
                -0.9309999942779541,
                -0.9340000152587891,
                -0.9319999814033508
            ],
            "t_fit": [
                4.052855670452118,
                2.5813160091638565,
                3.0585279166698456,
                2.1572025418281555,
                2.734810531139374
            ],
            "t_inference": [
                0.5183184146881104,
                0.31673383712768555,
                0.4643327295780182,
                0.2857305556535721,
                0.38554948568344116
            ],
            "hyperparams": [
                {
                    "in_dim": 33,
                    "n_classes": 2,
                    "feature_type": "SWIM",
                    "upscale_type": "identity",
                    "randfeat_xt_dim": 512,
                    "randfeat_x0_dim": 512,
                    "activation": "tanh",
                    "use_batchnorm": false,
                    "do_linesearch": false,
                    "n_layers": 5,
                    "hidden_dim": 147,
                    "l2_cls": 1.4233017025685193e-07,
                    "l2_ghat": 9.606973430900473,
                    "boost_lr": 0.6674193053804656,
                    "SWIM_scale": 1.9931383675493644
                },
                {
                    "in_dim": 33,
                    "n_classes": 2,
                    "feature_type": "SWIM",
                    "upscale_type": "identity",
                    "randfeat_xt_dim": 512,
                    "randfeat_x0_dim": 512,
                    "activation": "tanh",
                    "use_batchnorm": false,
                    "do_linesearch": false,
                    "n_layers": 3,
                    "hidden_dim": 107,
                    "l2_cls": 7.154643430757869e-05,
                    "l2_ghat": 0.008250148064753956,
                    "boost_lr": 0.15859327773409304,
                    "SWIM_scale": 1.3781422017337368
                },
                {
                    "in_dim": 33,
                    "n_classes": 2,
                    "feature_type": "SWIM",
                    "upscale_type": "identity",
                    "randfeat_xt_dim": 512,
                    "randfeat_x0_dim": 512,
                    "activation": "tanh",
                    "use_batchnorm": false,
                    "do_linesearch": false,
                    "n_layers": 5,
                    "hidden_dim": 124,
                    "l2_cls": 0.006534865559695535,
                    "l2_ghat": 0.007487021694760158,
                    "boost_lr": 0.4794949228708784,
                    "SWIM_scale": 1.489462031004055
                },
                {
                    "in_dim": 33,
                    "n_classes": 2,
                    "feature_type": "SWIM",
                    "upscale_type": "identity",
                    "randfeat_xt_dim": 512,
                    "randfeat_x0_dim": 512,
                    "activation": "tanh",
                    "use_batchnorm": false,
                    "do_linesearch": false,
                    "n_layers": 5,
                    "hidden_dim": 37,
                    "l2_cls": 0.0006115968852674797,
                    "l2_ghat": 0.001975562427027587,
                    "boost_lr": 0.13353124660935548,
                    "SWIM_scale": 1.1772031241603862
                },
                {
                    "in_dim": 33,
                    "n_classes": 2,
                    "feature_type": "SWIM",
                    "upscale_type": "identity",
                    "randfeat_xt_dim": 512,
                    "randfeat_x0_dim": 512,
                    "activation": "tanh",
                    "use_batchnorm": false,
                    "do_linesearch": false,
                    "n_layers": 4,
                    "hidden_dim": 17,
                    "l2_cls": 0.020192459298659482,
                    "l2_ghat": 0.002782575196989716,
                    "boost_lr": 0.6904127886188219,
                    "SWIM_scale": 1.0792638692473584
                }
            ]
        }
    }
}