{
    "44964": {
        "XGBoostRegressor": {
            "score_train": [
                0.139278843998909,
                0.14642323553562164,
                0.14106124639511108,
                0.14215248823165894,
                0.14061352610588074
            ],
            "score_test": [
                0.25408223271369934,
                0.2739715874195099,
                0.2594178318977356,
                0.269459992647171,
                0.263247013092041
            ],
            "t_fit": [
                52.27742586657405,
                52.507289143279195,
                45.80202064104378,
                20.86282773129642,
                45.46808325313032
            ],
            "t_inference": [
                1.7770237550139427,
                2.783903058618307,
                1.6825777553021908,
                0.5291065536439419,
                1.2403785903006792
            ],
            "hyperparams": [
                {
                    "objective": "reg:squarederror",
                    "alpha": 0.0006421161519802636,
                    "lambda": 0.012305975746380905,
                    "learning_rate": 0.014812034346050468,
                    "n_estimators": 544,
                    "max_depth": 10,
                    "subsample": 0.9212596797198498,
                    "colsample_bytree": 0.37254291389303124
                },
                {
                    "objective": "reg:squarederror",
                    "alpha": 7.583077174898687e-05,
                    "lambda": 28.67187158101224,
                    "learning_rate": 0.05639676365480825,
                    "n_estimators": 594,
                    "max_depth": 10,
                    "subsample": 0.4439494500594755,
                    "colsample_bytree": 0.4042488051038121
                },
                {
                    "objective": "reg:squarederror",
                    "alpha": 1.738127028998156e-05,
                    "lambda": 13.910538878301955,
                    "learning_rate": 0.027860623488680514,
                    "n_estimators": 1001,
                    "max_depth": 9,
                    "subsample": 0.7753383201084193,
                    "colsample_bytree": 0.47732756471555243
                },
                {
                    "objective": "reg:squarederror",
                    "alpha": 1.4451509705420143e-05,
                    "lambda": 0.14660109945265395,
                    "learning_rate": 0.026537867380171564,
                    "n_estimators": 495,
                    "max_depth": 9,
                    "subsample": 0.7635952105810265,
                    "colsample_bytree": 0.45438886632094827
                },
                {
                    "objective": "reg:squarederror",
                    "alpha": 0.009280217799405464,
                    "lambda": 0.003678995842256353,
                    "learning_rate": 0.011490588079993033,
                    "n_estimators": 1072,
                    "max_depth": 9,
                    "subsample": 0.9952689533745755,
                    "colsample_bytree": 0.408196187056482
                }
            ]
        }
    }
}