{
    "44973": {
        "XGBoostRegressor": {
            "score_train": [
                0.06016247719526291,
                0.0012589680263772607,
                0.015243474394083023,
                0.03175747022032738,
                0.07252241671085358
            ],
            "score_test": [
                0.20147758722305298,
                0.2000211477279663,
                0.19095438718795776,
                0.19369350373744965,
                0.20750106871128082
            ],
            "t_fit": [
                8.593824055045843,
                23.491728918626904,
                14.633278364315629,
                6.027458181604743,
                5.792506704106927
            ],
            "t_inference": [
                0.6794711165130138,
                1.1744820531457663,
                1.3740368969738483,
                0.5240966603159904,
                0.45233180932700634
            ],
            "hyperparams": [
                {
                    "objective": "reg:squarederror",
                    "alpha": 2.4935858279183426e-05,
                    "lambda": 0.4230208343624158,
                    "learning_rate": 0.023401614870212594,
                    "n_estimators": 1268,
                    "max_depth": 6,
                    "subsample": 0.5327910611683536,
                    "colsample_bytree": 0.9387295549378905
                },
                {
                    "objective": "reg:squarederror",
                    "alpha": 0.00011027174275395974,
                    "lambda": 1.8189816258716256,
                    "learning_rate": 0.05638534168949442,
                    "n_estimators": 1996,
                    "max_depth": 7,
                    "subsample": 0.702019517463674,
                    "colsample_bytree": 0.9181845534614663
                },
                {
                    "objective": "reg:squarederror",
                    "alpha": 2.527640602043916e-05,
                    "lambda": 1.5380925898501945,
                    "learning_rate": 0.04639375399372315,
                    "n_estimators": 1832,
                    "max_depth": 6,
                    "subsample": 0.672672624997173,
                    "colsample_bytree": 0.9173967295688897
                },
                {
                    "objective": "reg:squarederror",
                    "alpha": 0.007662366326642449,
                    "lambda": 0.11103875056159382,
                    "learning_rate": 0.03716246235819028,
                    "n_estimators": 1334,
                    "max_depth": 6,
                    "subsample": 0.7718502289887232,
                    "colsample_bytree": 0.9303819410558269
                },
                {
                    "objective": "reg:squarederror",
                    "alpha": 1.0443685194675441e-05,
                    "lambda": 1.6840286499589423,
                    "learning_rate": 0.033166063621204785,
                    "n_estimators": 836,
                    "max_depth": 6,
                    "subsample": 0.4841727144870199,
                    "colsample_bytree": 0.9947502345024206
                }
            ]
        }
    }
}